esp2_gateway_adapter/__init__.py
esp2_gateway_adapter/esp2_tcp_com.py
esp2_gateway_adapter/esp3_serial_com.py
esp2_gateway_adapter/esp3_tcp_com.py
esp2_gateway_adapter-0.2.21.dist-info/licenses/LICENSE
esp2_gateway_adapter-0.2.21.dist-info/METADATA
esp2_gateway_adapter-0.2.21.dist-info/WHEEL
esp2_gateway_adapter-0.2.21.dist-info/top_level.txt
esp2_gateway_adapter-0.2.21.dist-info/RECORD
