Metadata-Version: 2.4
Name: esp2_gateway_adapter
Version: 0.2.21
Summary: Protocol adapter from esp3 to esp2 for Home Assistant Eltako Integration
Home-page: https://github.com/grimmpp/esp2_gateway_adapter
Author: Philipp Grimm
License: MIT License
Requires-Python: >=3.7
License-File: LICENSE
Requires-Dist: eltako14bus>=0.0.46
Requires-Dist: enocean>=0.60.1
Requires-Dist: pyserial
Requires-Dist: pyserial-asyncio
Requires-Dist: aiocoap
Requires-Dist: zeroconf
Dynamic: author
Dynamic: description
Dynamic: description-content-type
Dynamic: home-page
Dynamic: license
Dynamic: license-file
Dynamic: requires-dist
Dynamic: requires-python
Dynamic: summary
